mlx_stft/__init__.py
mlx_stft/transforms.py
mlx_stft/utils.py
mlx_stft/version.py
mlx_stft/windows.py
mlx_stft-0.1.2.dist-info/licenses/LICENSE
mlx_stft-0.1.2.dist-info/METADATA
mlx_stft-0.1.2.dist-info/WHEEL
mlx_stft-0.1.2.dist-info/top_level.txt
mlx_stft-0.1.2.dist-info/RECORD
