Metadata-Version: 2.4
Name: mlx_stft
Version: 0.1.2
Summary: An implementation of STFT and Inverse STFT in mlx
Home-page: https://github.com/nuniz/mlx_stft
Author: Asaf Zorea
Author-email: zoreasaf@gmail.com
License: MIT
Classifier: Programming Language :: Python :: 3
Classifier: License :: OSI Approved :: MIT License
Classifier: Operating System :: MacOS
Requires-Python: >=3.6
License-File: LICENSE
Requires-Dist: mlx
Provides-Extra: dev
Requires-Dist: matplotlib; extra == "dev"
Requires-Dist: numpy; extra == "dev"
Requires-Dist: soundfile; extra == "dev"
Dynamic: author
Dynamic: author-email
Dynamic: classifier
Dynamic: description
Dynamic: description-content-type
Dynamic: home-page
Dynamic: license
Dynamic: license-file
Dynamic: provides-extra
Dynamic: requires-dist
Dynamic: requires-python
Dynamic: summary
